[
  {
    "type": "material",
    "ident": "c_superalloy_composite",
    "name": "Superalloy Composite",
    "density": 13,
    "specific_heat_liquid": 1,
    "specific_heat_solid": 0.75,
    "latent_heat": 303,
    "bash_resist": 3,
    "cut_resist": 4,
    "bullet_resist": 9,
    "acid_resist": 7,
    "fire_resist": 6,
    "elec_resist": 5,
    "chip_resist": 20,
    "repaired_with": "kevlar_plate",
    "dmg_adj": [ "marked", "dented", "smashed", "shattered" ],
    "bash_dmg_verb": "dented",
    "cut_dmg_verb": "scratched"
  }
]
